rtl/core_relu.v
// =============================================================================
// core_relu.v  —  ReLU Activation Core
// GPU Make | Xilinx Artix-7 target | Verilog POC
//
// Performs:  out = max(0, in)   on a stream of signed 32-bit values
// Latency   : 1 cycle
// Throughput: 1 result per clock (fully pipelined)
// =============================================================================

`timescale 1ns/1ps

module core_relu #(
    parameter DATA_WIDTH = 32
)(
    input  wire                        clk,
    input  wire                        rst_n,
    input  wire                        data_valid_in,           // upstream valid
    input  wire signed [DATA_WIDTH-1:0] data_in,               // signed input
    output reg                         data_valid_out,          // downstream valid
    output reg         [DATA_WIDTH-1:0] data_out               // rectified output (unsigned)
);

    // -------------------------------------------------------------------------
    // ReLU: clamp negative values to zero, pass positives through
    // One-cycle registered path for clean timing closure on FPGA
    // -------------------------------------------------------------------------
    always @(posedge clk or negedge rst_n) begin
        if (!rst_n) begin
            data_out       <= 0;
            data_valid_out <= 1'b0;
        end else begin
            data_valid_out <= data_valid_in;
            if (data_valid_in)
                data_out <= (data_in[DATA_WIDTH-1]) ? {DATA_WIDTH{1'b0}} : data_in;
            else
                data_out <= 0;
        end
    end

endmodule

rtl/core_mac.v
// =============================================================================
// core_mac.v  —  Multiply-Accumulate Core
// GPU Make | Xilinx Artix-7 target | Verilog POC
//
// Performs:  acc += A[i] * B[i]   for N elements (dot product)
// Datapath  : combinational multiply, registered accumulate
// Input     : 8-bit signed × 8-bit signed
// Output    : 32-bit signed accumulator
//
// Protocol:
//   1. Assert `start` for exactly 1 clock with the first (a_in, b_in) element.
//   2. Drive (a_in, b_in) for VEC_LEN consecutive clocks (including start clock).
//   3. After VEC_LEN clocks `valid` pulses high and `result` holds the answer.
// =============================================================================

`timescale 1ns/1ps

module core_mac #(
    parameter DATA_WIDTH = 8,
    parameter ACC_WIDTH  = 32,
    parameter VEC_LEN    = 16        // dot-product vector length
)(
    input  wire                          clk,
    input  wire                          rst_n,
    input  wire                          start,        // 1-cycle pulse: begin dot-product
    input  wire signed [DATA_WIDTH-1:0]  a_in,         // element of vector A
    input  wire signed [DATA_WIDTH-1:0]  b_in,         // element of vector B
    output reg  signed [ACC_WIDTH-1:0]   result,       // latched final result
    output reg                           valid          // 1-cycle pulse: result is ready
);

    // -------------------------------------------------------------------------
    // Combinational product (DSP48 will infer this on Artix-7)
    // -------------------------------------------------------------------------
    wire signed [2*DATA_WIDTH-1:0] product = a_in * b_in;

    // -------------------------------------------------------------------------
    // Accumulator + FSM
    // -------------------------------------------------------------------------
    reg signed [ACC_WIDTH-1:0]   acc;
    reg [$clog2(VEC_LEN):0]      count;
    reg                          running;

    always @(posedge clk or negedge rst_n) begin
        if (!rst_n) begin
            acc     <= 0;
            count   <= 0;
            running <= 1'b0;
            valid   <= 1'b0;
            result  <= 0;
        end else begin
            valid <= 1'b0;  // default deasserted

            if (start && !running) begin
                // First element: clear accumulator, count=1, capture product
                acc     <= {{(ACC_WIDTH - 2*DATA_WIDTH){product[2*DATA_WIDTH-1]}}, product};
                count   <= 1;
                running <= 1'b1;
            end else if (running) begin
                acc   <= acc + {{(ACC_WIDTH - 2*DATA_WIDTH){product[2*DATA_WIDTH-1]}}, product};
                count <= count + 1;

                if (count == VEC_LEN - 1) begin
                    // All elements consumed — latch result next cycle
                    result  <= acc + {{(ACC_WIDTH - 2*DATA_WIDTH){product[2*DATA_WIDTH-1]}}, product};
                    valid   <= 1'b1;
                    running <= 1'b0;
                    count   <= 0;
                end
            end
        end
    end

endmodule

rtl/top.v
// =============================================================================
// top.v  —  Top-Level GPU Module
// GPU Make | Xilinx Artix-7 target | Verilog POC
//
// Architecture:
//   Host → [Core A: MAC] → [Core B: ReLU] → Output
//
// The two cores form a minimal ML inference pipeline:
//   1. MAC core computes the dot product of two 8-bit vectors (one neuron)
//   2. ReLU core applies the activation function to the accumulator output
//
// This can be replicated N times in parallel for a full layer.
// =============================================================================

`timescale 1ns/1ps

module top #(
    parameter DATA_WIDTH = 8,
    parameter ACC_WIDTH  = 32,
    parameter VEC_LEN    = 16
)(
    input  wire                  clk,
    input  wire                  rst_n,

    // --- Host interface (simplified, no AXI for POC) ---
    input  wire                  start,              // begin computation
    input  wire signed [DATA_WIDTH-1:0] a_in,       // weight vector element
    input  wire signed [DATA_WIDTH-1:0] b_in,       // input vector element

    // --- Output ---
    output wire [ACC_WIDTH-1:0]  relu_out,           // activated neuron output
    output wire                  output_valid         // result is ready
);

    // -------------------------------------------------------------------------
    // Internal wires — connecting Core A (MAC) → Core B (ReLU)
    // -------------------------------------------------------------------------
    wire signed [ACC_WIDTH-1:0] mac_result;
    wire                        mac_valid;

    // -------------------------------------------------------------------------
    // Core A: MAC — Dot Product
    // -------------------------------------------------------------------------
    core_mac #(
        .DATA_WIDTH (DATA_WIDTH),
        .ACC_WIDTH  (ACC_WIDTH),
        .VEC_LEN    (VEC_LEN)
    ) u_mac (
        .clk    (clk),
        .rst_n  (rst_n),
        .start  (start),
        .a_in   (a_in),
        .b_in   (b_in),
        .result (mac_result),
        .valid  (mac_valid)
    );

    // -------------------------------------------------------------------------
    // Core B: ReLU — Activation Function
    // -------------------------------------------------------------------------
    core_relu #(
        .DATA_WIDTH (ACC_WIDTH)
    ) u_relu (
        .clk           (clk),
        .rst_n         (rst_n),
        .data_valid_in (mac_valid),
        .data_in       (mac_result),
        .data_valid_out(output_valid),
        .data_out      (relu_out)
    );

endmodule

sim/tb_top.v
// =============================================================================
// tb_top.v  —  Testbench for GPU Top-Level
// GPU Make | Simulation only (Icarus Verilog / ModelSim compatible)
//
// Tests:
//   T1 — Positive dot product  → ReLU passes through
//   T2 — Negative dot product  → ReLU clamps to zero
//   T3 — Zero vector           → Output is zero
// =============================================================================

`timescale 1ns/1ps

module tb_top;

    // -------------------------------------------------------------------------
    // Parameters (must match DUT)
    // -------------------------------------------------------------------------
    localparam DATA_WIDTH = 8;
    localparam ACC_WIDTH  = 32;
    localparam VEC_LEN    = 16;
    localparam CLK_PERIOD = 10;  // 10 ns → 100 MHz

    // -------------------------------------------------------------------------
    // DUT signals
    // -------------------------------------------------------------------------
    reg                          clk;
    reg                          rst_n;
    reg                          start;
    reg  signed [DATA_WIDTH-1:0] a_in;
    reg  signed [DATA_WIDTH-1:0] b_in;
    wire [ACC_WIDTH-1:0]         relu_out;
    wire                         output_valid;

    // -------------------------------------------------------------------------
    // DUT instantiation
    // -------------------------------------------------------------------------
    top #(
        .DATA_WIDTH (DATA_WIDTH),
        .ACC_WIDTH  (ACC_WIDTH),
        .VEC_LEN    (VEC_LEN)
    ) dut (
        .clk          (clk),
        .rst_n        (rst_n),
        .start        (start),
        .a_in         (a_in),
        .b_in         (b_in),
        .relu_out     (relu_out),
        .output_valid (output_valid)
    );

    // -------------------------------------------------------------------------
    // Clock generation: 100 MHz
    // -------------------------------------------------------------------------
    initial clk = 0;
    always #(CLK_PERIOD/2) clk = ~clk;

    // -------------------------------------------------------------------------
    // Task: feed VEC_LEN elements to the DUT
    //
    // Protocol (matches core_mac.v):
    //   Cycle 0 : start=1, a_in=val, b_in=val   (first element + start pulse)
    //   Cycle 1..VEC_LEN-1 : start=0, a_in=val, b_in=val
    //   After VEC_LEN cycles: inputs go idle
    // -------------------------------------------------------------------------
    task feed_vector;
        input signed [DATA_WIDTH-1:0] a_val;
        input signed [DATA_WIDTH-1:0] b_val;
        integer i;
        begin
            @(negedge clk);
            start = 1'b1;
            a_in  = a_val;
            b_in  = b_val;

            @(negedge clk);
            start = 1'b0;

            for (i = 1; i < VEC_LEN - 1; i = i + 1) begin
                a_in = a_val;
                b_in = b_val;
                @(negedge clk);
            end

            // Last element
            a_in = a_val;
            b_in = b_val;
            @(negedge clk);

            // Idle after vector is done
            a_in = 0;
            b_in = 0;
        end
    endtask

    // -------------------------------------------------------------------------
    // Task: wait for output_valid with timeout, then check result
    // -------------------------------------------------------------------------
    task check_output;
        input [ACC_WIDTH-1:0] expected;
        input integer         test_num;
        reg   [ACC_WIDTH-1:0] captured;
        begin
            captured = 0;

            // Poll for output_valid (max 60 cycles)
            begin : poll_loop
                integer k;
                for (k = 0; k < 60; k = k + 1) begin
                    @(posedge clk);
                    if (output_valid) begin
                        captured = relu_out;
                        disable poll_loop;
                    end
                end
            end

            #1; // tiny delta for signal settle

            if (captured === expected)
                $display("PASS T%0d: relu_out = %0d  (expected %0d)", test_num, captured, expected);
            else
                $display("FAIL T%0d: relu_out = %0d  (expected %0d)", test_num, captured, expected);
        end
    endtask

    // -------------------------------------------------------------------------
    // Stimulus
    // -------------------------------------------------------------------------
    initial begin
        $dumpfile("dump.vcd");
        $dumpvars(0, tb_top);

        // Reset sequence
        rst_n = 1'b0;
        start = 1'b0;
        a_in  = 0;
        b_in  = 0;
        repeat(4) @(posedge clk);
        @(negedge clk);
        rst_n = 1'b1;
        repeat(2) @(posedge clk);

        // ------------------------------------------------------------------
        // T1: Positive dot product
        //   a=[2,2,...,2]  b=[3,3,...,3]  N=16
        //   MAC = 2*3*16 = 96  →  ReLU(96) = 96
        // ------------------------------------------------------------------
        $display("\n--- T1: Positive dot product ---");
        fork
            feed_vector(8'sd2, 8'sd3);
            check_output(32'd96, 1);
        join
        repeat(5) @(posedge clk);

        // ------------------------------------------------------------------
        // T2: Negative dot product
        //   a=[2,...] b=[-3,...] N=16
        //   MAC = -96  →  ReLU(-96) = 0
        // ------------------------------------------------------------------
        $display("\n--- T2: Negative dot product (ReLU clamp) ---");
        fork
            feed_vector(8'sd2, -8'sd3);
            check_output(32'd0, 2);
        join
        repeat(5) @(posedge clk);

        // ------------------------------------------------------------------
        // T3: Zero vector
        //   a=0 b=0  →  MAC=0  →  ReLU(0) = 0
        // ------------------------------------------------------------------
        $display("\n--- T3: Zero vector ---");
        fork
            feed_vector(8'sd0, 8'sd0);
            check_output(32'd0, 3);
        join
        repeat(5) @(posedge clk);

        $display("\n=== Simulation complete ===\n");
        $finish;
    end

endmodule

sim/dump.vcd
$date
	Thu May 14 17:21:06 2026
$end
$version
	Icarus Verilog
$end
$timescale
	1ps
$end
$scope module tb_top $end
$var wire 32 ! relu_out [31:0] $end
$var wire 1 " output_valid $end
$var parameter 32 # ACC_WIDTH $end
$var parameter 32 $ CLK_PERIOD $end
$var parameter 32 % DATA_WIDTH $end
$var parameter 32 & VEC_LEN $end
$var reg 8 ' a_in [7:0] $end
$var reg 8 ( b_in [7:0] $end
$var reg 1 ) clk $end
$var reg 1 * rst_n $end
$var reg 1 + start $end
$scope module dut $end
$var wire 8 , a_in [7:0] $end
$var wire 8 - b_in [7:0] $end
$var wire 1 ) clk $end
$var wire 1 * rst_n $end
$var wire 1 + start $end
$var wire 32 . relu_out [31:0] $end
$var wire 1 " output_valid $end
$var wire 1 / mac_valid $end
$var wire 32 0 mac_result [31:0] $end
$var parameter 32 1 ACC_WIDTH $end
$var parameter 32 2 DATA_WIDTH $end
$var parameter 32 3 VEC_LEN $end
$scope module u_mac $end
$var wire 8 4 a_in [7:0] $end
$var wire 8 5 b_in [7:0] $end
$var wire 1 ) clk $end
$var wire 1 * rst_n $end
$var wire 1 + start $end
$var wire 16 6 product [15:0] $end
$var parameter 32 7 ACC_WIDTH $end
$var parameter 32 8 DATA_WIDTH $end
$var parameter 32 9 VEC_LEN $end
$var reg 32 : acc [31:0] $end
$var reg 5 ; count [4:0] $end
$var reg 32 < result [31:0] $end
$var reg 1 = running $end
$var reg 1 / valid $end
$upscope $end
$scope module u_relu $end
$var wire 1 ) clk $end
$var wire 32 > data_in [31:0] $end
$var wire 1 / data_valid_in $end
$var wire 1 * rst_n $end
$var parameter 32 ? DATA_WIDTH $end
$var reg 32 @ data_out [31:0] $end
$var reg 1 " data_valid_out $end
$upscope $end
$upscope $end
$scope task check_output $end
$var reg 32 A captured [31:0] $end
$var reg 32 B expected [31:0] $end
$var integer 32 C test_num [31:0] $end
$scope begin poll_loop $end
$var integer 32 D k [31:0] $end
$upscope $end
$upscope $end
$scope task feed_vector $end
$var reg 8 E a_val [7:0] $end
$var reg 8 F b_val [7:0] $end
$var integer 32 G i [31:0] $end
$upscope $end
$upscope $end
$enddefinitions $end
$comment Show the parameter values. $end
$dumpall
b100000 ?
b10000 9
b1000 8
b100000 7
b10000 3
b1000 2
b100000 1
b10000 &
b1000 %
b1010 $
b100000 #
$end
#0
$dumpvars
bx G
bx F
bx E
bx D
bx C
bx B
bx A
b0 @
b0 >
0=
b0 <
b0 ;
b0 :
b0 6
b0 5
b0 4
b0 0
0/
b0 .
b0 -
b0 ,
0+
0*
0)
b0 (
b0 '
0"
b0 !
$end
#5000
1)
#10000
0)
#15000
1)
#20000
0)
#25000
1)
#30000
0)
#35000
1)
#40000
1*
0)
#45000
1)
#50000
0)
#55000
b11 F
b10 E
b0 D
b0 A
b1 C
b1100000 B
1)
#60000
b110 6
b11 (
b11 -
b11 5
b10 '
b10 ,
b10 4
1+
0)
#65000
1=
b1 ;
b110 :
b1 D
1)
#70000
b1 G
0+
0)
#75000
b10 ;
b1100 :
b10 D
1)
#80000
b10 G
0)
#85000
b11 ;
b10010 :
b11 D
1)
#90000
b11 G
0)
#95000
b100 ;
b11000 :
b100 D
1)
#100000
b100 G
0)
#105000
b101 ;
b11110 :
b101 D
1)
#110000
b101 G
0)
#115000
b110 ;
b100100 :
b110 D
1)
#120000
b110 G
0)
#125000
b111 ;
b101010 :
b111 D
1)
#130000
b111 G
0)
#135000
b1000 ;
b110000 :
b1000 D
1)
#140000
b1000 G
0)
#145000
b1001 ;
b110110 :
b1001 D
1)
#150000
b1001 G
0)
#155000
b1010 ;
b111100 :
b1010 D
1)
#160000
b1010 G
0)
#165000
b1011 ;
b1000010 :
b1011 D
1)
#170000
b1011 G
0)
#175000
b1100 ;
b1001000 :
b1100 D
1)
#180000
b1100 G
0)
#185000
b1101 ;
b1001110 :
b1101 D
1)
#190000
b1101 G
0)
#195000
b1110 ;
b1010100 :
b1110 D
1)
#200000
b1110 G
0)
#205000
b1111 ;
b1011010 :
b1111 D
1)
#210000
b1111 G
0)
#215000
0=
1/
b1100000 0
b1100000 <
b1100000 >
b0 ;
b1100000 :
b10000 D
1)
#220000
b0 (
b0 -
b0 5
b0 6
b0 '
b0 ,
b0 4
0)
#225000
b1100000 !
b1100000 .
b1100000 @
1"
0/
b10001 D
1)
#230000
0)
#235000
b0 !
b0 .
b0 @
0"
b1100000 A
1)
#240000
0)
#245000
1)
#250000
0)
#255000
1)
#260000
0)
#265000
1)
#270000
0)
#275000
1)
#280000
0)
#285000
b11111101 F
b0 D
b0 A
b10 C
b0 B
1)
#290000
b1111111111111010 6
b11111101 (
b11111101 -
b11111101 5
b10 '
b10 ,
b10 4
1+
0)
#295000
1=
b1 ;
b11111111111111111111111111111010 :
b1 D
1)
#300000
b1 G
0+
0)
#305000
b10 ;
b11111111111111111111111111110100 :
b10 D
1)
#310000
b10 G
0)
#315000
b11 ;
b11111111111111111111111111101110 :
b11 D
1)
#320000
b11 G
0)
#325000
b100 ;
b11111111111111111111111111101000 :
b100 D
1)
#330000
b100 G
0)
#335000
b101 ;
b11111111111111111111111111100010 :
b101 D
1)
#340000
b101 G
0)
#345000
b110 ;
b11111111111111111111111111011100 :
b110 D
1)
#350000
b110 G
0)
#355000
b111 ;
b11111111111111111111111111010110 :
b111 D
1)
#360000
b111 G
0)
#365000
b1000 ;
b11111111111111111111111111010000 :
b1000 D
1)
#370000
b1000 G
0)
#375000
b1001 ;
b11111111111111111111111111001010 :
b1001 D
1)
#380000
b1001 G
0)
#385000
b1010 ;
b11111111111111111111111111000100 :
b1010 D
1)
#390000
b1010 G
0)
#395000
b1011 ;
b11111111111111111111111110111110 :
b1011 D
1)
#400000
b1011 G
0)
#405000
b1100 ;
b11111111111111111111111110111000 :
b1100 D
1)
#410000
b1100 G
0)
#415000
b1101 ;
b11111111111111111111111110110010 :
b1101 D
1)
#420000
b1101 G
0)
#425000
b1110 ;
b11111111111111111111111110101100 :
b1110 D
1)
#430000
b1110 G
0)
#435000
b1111 ;
b11111111111111111111111110100110 :
b1111 D
1)
#440000
b1111 G
0)
#445000
0=
1/
b11111111111111111111111110100000 0
b11111111111111111111111110100000 <
b11111111111111111111111110100000 >
b0 ;
b11111111111111111111111110100000 :
b10000 D
1)
#450000
b0 (
b0 -
b0 5
b0 6
b0 '
b0 ,
b0 4
0)
#455000
0/
1"
b10001 D
1)
#460000
0)
#465000
0"
1)
#470000
0)
#475000
1)
#480000
0)
#485000
1)
#490000
0)
#495000
1)
#500000
0)
#505000
1)
#510000
0)
#515000
b0 F
b0 E
b0 D
b11 C
1)
#520000
1+
0)
#525000
1=
b1 ;
b0 :
b1 D
1)
#530000
b1 G
0+
0)
#535000
b10 ;
b10 D
1)
#540000
b10 G
0)
#545000
b11 ;
b11 D
1)
#550000
b11 G
0)
#555000
b100 ;
b100 D
1)
#560000
b100 G
0)
#565000
b101 ;
b101 D
1)
#570000
b101 G
0)
#575000
b110 ;
b110 D
1)
#580000
b110 G
0)
#585000
b111 ;
b111 D
1)
#590000
b111 G
0)
#595000
b1000 ;
b1000 D
1)
#600000
b1000 G
0)
#605000
b1001 ;
b1001 D
1)
#610000
b1001 G
0)
#615000
b1010 ;
b1010 D
1)
#620000
b1010 G
0)
#625000
b1011 ;
b1011 D
1)
#630000
b1011 G
0)
#635000
b1100 ;
b1100 D
1)
#640000
b1100 G
0)
#645000
b1101 ;
b1101 D
1)
#650000
b1101 G
0)
#655000
b1110 ;
b1110 D
1)
#660000
b1110 G
0)
#665000
b1111 ;
b1111 D
1)
#670000
b1111 G
0)
#675000
0=
1/
b0 0
b0 <
b0 >
b0 ;
b10000 D
1)
#680000
0)
#685000
1"
0/
b10001 D
1)
#690000
0)
#695000
0"
1)
